DNASkittleUtils/Annotations.py
DNASkittleUtils/CommandLineUtils.py
DNASkittleUtils/Contigs.py
DNASkittleUtils/DDVUtils.py
DNASkittleUtils/FastaStats.py
DNASkittleUtils/__init__.py
DNASkittleUtils-1.0.13.dist-info/LICENSE
DNASkittleUtils-1.0.13.dist-info/METADATA
DNASkittleUtils-1.0.13.dist-info/WHEEL
DNASkittleUtils-1.0.13.dist-info/top_level.txt
DNASkittleUtils-1.0.13.dist-info/RECORD
