Metadata-Version: 2.1
Name: DNASkittleUtils
Version: 1.0.13
Summary: Bioinformatics functions that have been useful in multiple projects.  Manipulating FASTA files, executing pipelines, etc.
Home-page: https://github.com/josiahseaman/DNASkittleUtils
Author: Josiah Seaman
Author-email: josiah@newline.us
License: UNKNOWN
Download-URL: https://github.com/josiahseaman/DNASkittleUtils
Keywords: bioinformatics,dna,fasta
Platform: UNKNOWN
Classifier: Development Status :: 5 - Production/Stable
Classifier: Intended Audience :: Science/Research
Classifier: License :: OSI Approved :: Apache Software License
Classifier: Operating System :: OS Independent
Classifier: Programming Language :: Python
Classifier: Programming Language :: Python :: 2
Classifier: Programming Language :: Python :: 2.7
Classifier: Programming Language :: Python :: 3
Classifier: Programming Language :: Python :: 3.4
Classifier: Programming Language :: Python :: 3.5
Classifier: Programming Language :: Python :: 3.6
Classifier: Programming Language :: Python :: 3.7
Classifier: Topic :: Scientific/Engineering :: Bio-Informatics
